README.txt
fail.py
setup.py
fail.egg-info/PKG-INFO
fail.egg-info/SOURCES.txt
fail.egg-info/dependency_links.txt
fail.egg-info/entry_points.txt
fail.egg-info/not-zip-safe
fail.egg-info/top_level.txt