Metadata-Version: 1.0
Name: fail
Version: 0.0
Summary: run a program until it fails and gather statistics
Home-page: UNKNOWN
Author: Jeff Hammel
Author-email: k0scist@gmail.com
License: UNKNOWN
Platform: UNKNOWN
